{"filename":"[C14-34] 19v.jpg","pages":[{"regions":[{"bounding_box":{"fromX":872,"toX":2279,"fromY":270,"toY":480},"id":33948,"type":"title"},{"bounding_box":{"fromX":612,"toX":3015,"fromY":343,"toY":544},"id":33949,"type":"empty_staff"},{"bounding_box":{"fromX":624,"toX":3004,"fromY":640,"toY":844},"id":33950,"type":"empty_staff"},{"bounding_box":{"fromX":711,"toX":1205,"fromY":856,"toY":1011},"id":33961,"type":"text"},{"bounding_box":{"fromX":624,"toX":3022,"fromY":924,"toY":1153},"id":33962,"type":"staff","symbols":[{"agnostic_symbol_type":"clef.G","approximateX":733,"id":191633,"position_in_staff":"L2"},{"agnostic_symbol_type":"accidental.flat","approximateX":842,"id":191634,"position_in_staff":"L3"},{"agnostic_symbol_type":"digit.2","approximateX":951,"id":191635,"position_in_staff":"L4"},{"agnostic_symbol_type":"digit.4","approximateX":951,"id":191636,"position_in_staff":"L2"},{"agnostic_symbol_type":"note.eighth_up","approximateX":1060,"id":191637,"position_in_staff":"S2"},{"agnostic_symbol_type":"note.eighth_down","approximateX":1169,"id":191638,"position_in_staff":"L3"},{"agnostic_symbol_type":"verticalLine","approximateX":1278,"id":191639,"position_in_staff":"L1"},{"agnostic_symbol_type":"note.quarter_down","approximateX":1387,"id":191640,"position_in_staff":"S3"},{"agnostic_symbol_type":"note.quarter_down","approximateX":1496,"id":191641,"position_in_staff":"L4"},{"agnostic_symbol_type":"verticalLine","approximateX":1605,"id":191642,"position_in_staff":"L1"},{"agnostic_symbol_type":"note.eighth_down","approximateX":1714,"id":191643,"position_in_staff":"S3"},{"agnostic_symbol_type":"dot","approximateX":1823,"id":191644,"position_in_staff":"S3"},{"agnostic_symbol_type":"note.sixteenth_down","approximateX":1932,"id":191645,"position_in_staff":"S3"},{"agnostic_symbol_type":"note.eighth_down","approximateX":2041,"id":191646,"position_in_staff":"L4"},{"agnostic_symbol_type":"note.eighth_down","approximateX":2150,"id":191647,"position_in_staff":"S3"},{"agnostic_symbol_type":"verticalLine","approximateX":2259,"id":191648,"position_in_staff":"L1"},{"agnostic_symbol_type":"note.eighth_down","approximateX":2368,"id":191649,"position_in_staff":"L3"},{"agnostic_symbol_type":"note.sixteenth_down","approximateX":2477,"id":191650,"position_in_staff":"L3"},{"agnostic_symbol_type":"note.sixteenth_down","approximateX":2586,"id":191651,"position_in_staff":"L3"},{"agnostic_symbol_type":"note.eighth_down","approximateX":2695,"id":191652,"position_in_staff":"L3"},{"agnostic_symbol_type":"note.eighth_down","approximateX":2804,"id":191653,"position_in_staff":"L3"}]},{"bounding_box":{"fromX":907,"toX":3070,"fromY":1070,"toY":1257},"id":33967,"type":"lyrics"},{"bounding_box":{"fromX":607,"toX":3022,"fromY":1223,"toY":1427},"id":33963,"type":"staff","symbols":[{"agnostic_symbol_type":"verticalLine","approximateX":722,"id":191654,"position_in_staff":"L1"},{"agnostic_symbol_type":"note.eighth_down","approximateX":837,"id":191655,"position_in_staff":"S3"},{"agnostic_symbol_type":"note.eighth_up","approximateX":952,"id":191656,"position_in_staff":"S2"},{"agnostic_symbol_type":"note.eighth_up","approximateX":1067,"id":191657,"position_in_staff":"S2"},{"agnostic_symbol_type":"note.eighth_down","approximateX":1182,"id":191658,"position_in_staff":"L3"},{"agnostic_symbol_type":"verticalLine","approximateX":1297,"id":191659,"position_in_staff":"L1"},{"agnostic_symbol_type":"note.quarter_down","approximateX":1412,"id":191660,"position_in_staff":"S3"},{"agnostic_symbol_type":"note.quarter_down","approximateX":1527,"id":191661,"position_in_staff":"L4"},{"agnostic_symbol_type":"verticalLine","approximateX":1642,"id":191662,"position_in_staff":"L1"},{"agnostic_symbol_type":"note.eighth_down","approximateX":1757,"id":191663,"position_in_staff":"S3"},{"agnostic_symbol_type":"dot","approximateX":1872,"id":191664,"position_in_staff":"S3"},{"agnostic_symbol_type":"note.sixteenth_down","approximateX":1987,"id":191665,"position_in_staff":"S3"},{"agnostic_symbol_type":"note.eighth_down","approximateX":2102,"id":191666,"position_in_staff":"L4"},{"agnostic_symbol_type":"note.eighth_down","approximateX":2217,"id":191667,"position_in_staff":"S3"},{"agnostic_symbol_type":"verticalLine","approximateX":2332,"id":191668,"position_in_staff":"L1"},{"agnostic_symbol_type":"note.eighth_down","approximateX":2447,"id":191669,"position_in_staff":"L3"},{"agnostic_symbol_type":"note.sixteenth_down","approximateX":2562,"id":191670,"position_in_staff":"L3"},{"agnostic_symbol_type":"note.sixteenth_down","approximateX":2677,"id":191671,"position_in_staff":"L3"},{"agnostic_symbol_type":"note.eighth_down","approximateX":2792,"id":191672,"position_in_staff":"S3"},{"agnostic_symbol_type":"note.eighth_down","approximateX":2907,"id":191673,"position_in_staff":"L3"}]},{"bounding_box":{"fromX":650,"toX":3096,"fromY":1367,"toY":1533},"id":33966,"type":"lyrics"},{"bounding_box":{"fromX":622,"toX":3010,"fromY":1517,"toY":1738},"id":33964,"type":"staff","symbols":[{"agnostic_symbol_type":"verticalLine","approximateX":1099,"id":191674,"position_in_staff":"L1"},{"agnostic_symbol_type":"note.quarter_up","approximateX":1576,"id":191675,"position_in_staff":"S2"},{"agnostic_symbol_type":"rest.quarter","approximateX":2053,"id":191676,"position_in_staff":"L3"},{"agnostic_symbol_type":"verticalLine","approximateX":2530,"id":191677,"position_in_staff":"L1"}]},{"bounding_box":{"fromX":659,"toX":912,"fromY":1689,"toY":1828},"id":33965,"type":"lyrics"},{"bounding_box":{"fromX":626,"toX":3043,"fromY":1819,"toY":2010},"id":33951,"type":"empty_staff"},{"bounding_box":{"fromX":1308,"toX":2598,"fromY":2033,"toY":3597},"id":33960,"type":"text"},{"bounding_box":{"fromX":628,"toX":3039,"fromY":2102,"toY":2284},"id":33952,"type":"empty_staff"},{"bounding_box":{"fromX":643,"toX":3046,"fromY":2383,"toY":2596},"id":33953,"type":"empty_staff"},{"bounding_box":{"fromX":647,"toX":3051,"fromY":2690,"toY":2865},"id":33954,"type":"empty_staff"},{"bounding_box":{"fromX":662,"toX":3056,"fromY":2968,"toY":3165},"id":33955,"type":"empty_staff"},{"bounding_box":{"fromX":664,"toX":3058,"fromY":3271,"toY":3459},"id":33956,"type":"empty_staff"},{"bounding_box":{"fromX":669,"toX":3069,"fromY":3575,"toY":3740},"id":33957,"type":"empty_staff"},{"bounding_box":{"fromX":671,"toX":2918,"fromY":3597,"toY":3842},"id":33959,"type":"text"},{"bounding_box":{"fromX":541,"toX":720,"fromY":3833,"toY":3925},"id":33958,"type":"text"}],"bounding_box":{"fromX":0,"toX":3227,"fromY":0,"toY":4049},"id":3546}],"id":3210,"collection":""}