{"filename":"[C14-48] 26v.jpg","pages":[{"regions":[{"bounding_box":{"fromX":754,"toX":2853,"fromY":204,"toY":518},"id":34255,"type":"title"},{"bounding_box":{"fromX":573,"toX":2979,"fromY":323,"toY":550},"id":34256,"type":"empty_staff"},{"bounding_box":{"fromX":588,"toX":2975,"fromY":627,"toY":838},"id":34257,"type":"empty_staff"},{"bounding_box":{"fromX":550,"toX":3014,"fromY":878,"toY":1438},"id":34270,"type":"text"},{"bounding_box":{"fromX":590,"toX":2989,"fromY":919,"toY":1106},"id":34258,"type":"empty_staff"},{"bounding_box":{"fromX":606,"toX":3008,"fromY":1200,"toY":1404},"id":34259,"type":"empty_staff"},{"bounding_box":{"fromX":665,"toX":966,"fromY":1431,"toY":1574},"id":34269,"type":"text"},{"bounding_box":{"fromX":602,"toX":3071,"fromY":1483,"toY":1717},"id":32848,"type":"staff"},{"bounding_box":{"fromX":884,"toX":2890,"fromY":1637,"toY":1794},"id":34271,"type":"lyrics"},{"bounding_box":{"fromX":606,"toX":3029,"fromY":1812,"toY":2004},"id":34260,"type":"empty_staff"},{"bounding_box":{"fromX":583,"toX":3096,"fromY":2030,"toY":3211},"id":34268,"type":"text"},{"bounding_box":{"fromX":595,"toX":3049,"fromY":2072,"toY":2287},"id":34261,"type":"empty_staff"},{"bounding_box":{"fromX":629,"toX":3036,"fromY":2395,"toY":2579},"id":34262,"type":"empty_staff"},{"bounding_box":{"fromX":625,"toX":3026,"fromY":2687,"toY":2855},"id":34263,"type":"empty_staff"},{"bounding_box":{"fromX":639,"toX":3033,"fromY":2975,"toY":3148},"id":34264,"type":"empty_staff"},{"bounding_box":{"fromX":630,"toX":3028,"fromY":3269,"toY":3454},"id":34265,"type":"empty_staff"},{"bounding_box":{"fromX":665,"toX":3035,"fromY":3564,"toY":3734},"id":34266,"type":"empty_staff"},{"bounding_box":{"fromX":580,"toX":782,"fromY":3835,"toY":3931},"id":34267,"type":"text"}],"bounding_box":{"fromX":0,"toX":3250,"fromY":0,"toY":4033},"id":3501}],"id":3224,"collection":""}